{
    "time": 0,
    "fare basis code": 1,
    "economy": 2,
    "flight time": 3,
    "flight duration": 4,
    "airline name": 5,
    "superlative": 6,
    "depart date": 7,
    "connect": 8,
    "return time": 9,
    "flight class": 10,
    "arrive date": 11,
    "depart time": 12,
    "meal": 13,
    "round trip": 14,
    "aircraft code": 15,
    "at time": 16,
    "airport name": 17,
    "to location": 18,
    "stop location": 19,
    "days code": 20,
    "flight number": 21,
    "duration": 22,
    "class type": 23,
    "meal description": 24,
    "from location": 25,
    "alternative": 26,
    "date": 27,
    "relative to today": 28,
    "arrive time": 29,
    "transport type": 30,
    "relative cost": 31,
    "O": 32,
    "return date": 33,
    "restriction code": 34,
    "location": 35,
    "fare amount": 36,
    "relative time": 37,
    "airport code": 38,
    "in location": 39,
    "airline code": 40
}